parser_functions/__about__.py
parser_functions/__init__.py
parser_functions/__main__.py
parser_functions/arithmetic.py
parser_functions/combinators.py
parser_functions/csv.py
parser_functions/dictionary.py
parser_functions/abnf/__init__.py
parser_functions/abnf/ast.py
parser_functions/abnf/codegen.py
parser_functions/abnf/parser.py
parser_functions/abnf/visitors.py
parser_functions/cellular_automata/__init__.py
parser_functions/cellular_automata/ca.abnf
parser_functions/cellular_automata/parser.py
parser_functions/cellular_automata/visitors.py
parser_functions/json/__init__.py
parser_functions/json/json-trail.abnf
parser_functions/json/json.abnf
parser_functions/json/permissive_example.json
parser_functions/json/permissive_parser.py
parser_functions/json/permissive_visitor.py
parser_functions/json/strict_example.json
parser_functions/json/strict_parser.py
parser_functions/json/strict_visitor.py
parser_functions-0.0.4.dist-info/METADATA
parser_functions-0.0.4.dist-info/WHEEL
parser_functions-0.0.4.dist-info/licenses/LICENSE.txt
parser_functions-0.0.4.dist-info/RECORD
