Metadata-Version: 2.3
Name: parser-functions
Version: 0.0.4
Project-URL: Documentation, https://github.com/stealthycoin/parser-functions#readme
Project-URL: Issues, https://github.com/stealthycoin/parser-functions/issues
Project-URL: Source, https://github.com/stealthycoin/parser-functions
Author-email: stealthycoin <stealthycoin@users.noreply.github.com>
License-Expression: MIT
License-File: LICENSE.txt
Classifier: Development Status :: 4 - Beta
Classifier: Programming Language :: Python
Classifier: Programming Language :: Python :: 3.12
Classifier: Programming Language :: Python :: Implementation :: CPython
Requires-Python: >=3.12
